README.md
setup.cfg
setup.py
distributions_km/Binomialdistribution.py
distributions_km/Gaussiandistribution.py
distributions_km/Generaldistribution.py
distributions_km/__init__.py
distributions_km.egg-info/PKG-INFO
distributions_km.egg-info/SOURCES.txt
distributions_km.egg-info/dependency_links.txt
distributions_km.egg-info/not-zip-safe
distributions_km.egg-info/top_level.txt