Metadata-Version: 1.0
Name: distributions-km
Version: 0.1
Summary: Gaussian and Binomial distributions
Home-page: UNKNOWN
Author: Muralidhar Kuluru
Author-email: muralidhark36@gmail.com
License: UNKNOWN
Platform: UNKNOWN
